nersemble_benchmark/__init__.py
nersemble_benchmark/constants.py
nersemble_benchmark/env.py
nersemble_benchmark/data/__init__.py
nersemble_benchmark/data/benchmark_data.py
nersemble_benchmark/data/submission_data.py
nersemble_benchmark/models/__init__.py
nersemble_benchmark/models/flame.py
nersemble_benchmark/scripts/__init__.py
nersemble_benchmark/scripts/download_data.py
nersemble_benchmark/util/__init__.py
nersemble_benchmark/util/download.py
nersemble_benchmark/util/metadata.py
nersemble_benchmark/util/security.py
nersemble_benchmark/util/video.py
nersemble_benchmark-0.0.16.dist-info/METADATA
nersemble_benchmark-0.0.16.dist-info/WHEEL
nersemble_benchmark-0.0.16.dist-info/entry_points.txt
nersemble_benchmark-0.0.16.dist-info/top_level.txt
nersemble_benchmark-0.0.16.dist-info/RECORD
