Metadata-Version: 2.4
Name: nersemble_benchmark
Version: 0.0.16
Summary: Official toolkit for the NeRSemble Photorealistic 3D Head Avatar Benchmark
Author-email: Tobias Kirschstein <tobias.kirschstein@gmail.com>
License: Apache 2.0
Classifier: Development Status :: 3 - Alpha
Classifier: Programming Language :: Python :: 3
Classifier: Operating System :: OS Independent
Requires-Python: >=3.8.0
Requires-Dist: tyro
Requires-Dist: environs
Requires-Dist: elias
Requires-Dist: dreifus
Requires-Dist: tqdm
Requires-Dist: open3d
Requires-Dist: flame-model
Requires-Dist: mediapy
Requires-Dist: imageio[pyav]
Provides-Extra: dev
